markipy/__init__.py
markipy/basic/__init__.py
markipy/basic/async_process.py
markipy/basic/atom.py
markipy/basic/channel.py
markipy/basic/filesystem.py
markipy/basic/hdf.py
markipy/basic/logger.py
markipy/basic/perf.py
markipy/basic/process.py
markipy/basic/rsync.py
markipy/basic/style.py
markipy/basic/terminator.py
markipy/basic/thread.py
markipy/basic/time.py
markipy/basic/watchers.py
markipy/basic/yml.py
markipy/basic/test/__init__.py
markipy/basic/test/test_atom.py
markipy/basic/test/test_channel.py
markipy/basic/test/test_filesystem.py
markipy/basic/test/test_logger.py
markipy/basic/test/test_performance.py
markipy/basic/test/test_process.py
markipy/basic/test/test_style.py
markipy/basic/test/test_thread.py
markipy/basic/test/test_watcher.py
markipy/gui/__init__.py
markipy/gui/app/__init__.py
markipy/gui/app/app.py
markipy/gui/controllers/__init__.py
markipy/gui/controllers/list.py
markipy/gui/examples/components.py
markipy/gui/examples/hello_world.py
markipy/gui/examples/selectable_list.py
markipy/gui/examples/state_transition.py
markipy/gui/resource/earth.960x540.jpg
markipy/gui/views/__init__.py
markipy/gui/views/view.py
markipy/gui/views/qml/components.qml
markipy/gui/views/qml/hello_world.qml
markipy/gui/views/qml/list.qml
markipy/gui/views/qml/state_transition.qml
markipy/gui/views/qml/components/Cell.qml
markipy/ros/__init__.py
markipy/ros/bag/__init__.py
markipy/ros/bag/check_datalogger_delay.py
markipy/ros/bag/fix.py
markipy/ros/bag/io.py
markipy/script/__init__.py
markipy/script/markipy.py
markipy-0.1.3.dist-info/LICENSE
markipy-0.1.3.dist-info/METADATA
markipy-0.1.3.dist-info/WHEEL
markipy-0.1.3.dist-info/entry_points.txt
markipy-0.1.3.dist-info/top_level.txt
markipy-0.1.3.dist-info/RECORD
