Metadata-Version: 2.1
Name: markipy
Version: 0.1.3
Summary: MrkPy LIB
Home-page: https://github.com/MarkNo1/MarkPy
Author: Marco T.
License: GNU AFFERO GENERAL PUBLIC LICENSE
Requires-Dist: html-testRunner
Requires-Dist: wget
Requires-Dist: watchdog
Requires-Dist: tqdm
Requires-Dist: pandas
Requires-Dist: numpy
Requires-Dist: emoji
Requires-Dist: PySide2
Requires-Dist: setuptools
Requires-Dist: twine
Requires-Dist: matplotlib
Requires-Dist: pycryptodomex
Requires-Dist: python-gnupg
Requires-Dist: rospkg
Requires-Dist: rosbag
Requires-Dist: rospy
Requires-Dist: tables
